bls_transformer/BLS.py
bls_transformer/__init__.py
bls_transformer-1.1.0.dist-info/LICENSE
bls_transformer-1.1.0.dist-info/METADATA
bls_transformer-1.1.0.dist-info/WHEEL
bls_transformer-1.1.0.dist-info/top_level.txt
bls_transformer-1.1.0.dist-info/RECORD
