Metadata-Version: 2.1
Name: bls-transformer
Version: 1.1.0
Summary: An easy-to-use library to access Bureau of Labor Statistics data and transform the raw JSON into pandas DataFrames.
Author-email: Ryan Sherby <ryan.m.sherby@gmail.com>
License: MIT License
Project-URL: Homepage, https://github.com/ryansherby/BLS-Transformer
Project-URL: Documentation, https://github.com/ryansherby/BLS-Transformer/wiki
Keywords: BLS,data,transformer,json,economics,timeseries,CPI,unemployment
Classifier: License :: OSI Approved :: MIT License
Classifier: Programming Language :: Python
Classifier: Programming Language :: Python :: 3
Requires-Python: >=3.9
License-File: LICENSE
Requires-Dist: requests
Requires-Dist: pandas
Requires-Dist: numpy
